webgym/__init__.py
webgym/envs.py
webgym/miniwob_env.py
webgym/miniwob/__init__.py
webgym/miniwob/action.py
webgym/miniwob/environment.py
webgym/miniwob/fields.py
webgym/miniwob/instance.py
webgym/miniwob/reward.py
webgym/miniwob/screenshot.py
webgym/miniwob/state.py
webgym/miniwob/utils.py
webgym/miniwob/html/.gitignore
webgym/miniwob/html/common/shapes.js
webgym/miniwob/html/common/ui_utils.js
webgym/miniwob/html/common/special/book-flight/domestic.js
webgym/miniwob/html/common/special/checkbox-numbers/ch_0.png
webgym/miniwob/html/common/special/checkbox-numbers/ch_1.png
webgym/miniwob/html/common/special/checkbox-numbers/ch_2.png
webgym/miniwob/html/common/special/checkbox-numbers/ch_3.png
webgym/miniwob/html/common/special/checkbox-numbers/ch_4.png
webgym/miniwob/html/common/special/checkbox-numbers/ch_5.png
webgym/miniwob/html/common/special/checkbox-numbers/ch_6.png
webgym/miniwob/html/common/special/checkbox-numbers/ch_7.png
webgym/miniwob/html/common/special/checkbox-numbers/ch_8.png
webgym/miniwob/html/common/special/checkbox-numbers/ch_9.png
webgym/miniwob/html/common/special/click-pie/raphael.icons.min.js
webgym/miniwob/html/common/special/click-pie/raphael.min.js
webgym/miniwob/html/common/special/click-pie/wheelnav.min.js
webgym/miniwob/html/common/special/drag-cube/blank.png
webgym/miniwob/html/common/special/drag-cube/cube.css
webgym/miniwob/html/common/special/drag-cube/cube.js
webgym/miniwob/html/common/special/email-inbox/delete.png
webgym/miniwob/html/common/special/email-inbox/email-inbox.css
webgym/miniwob/html/common/special/email-inbox/forward.png
webgym/miniwob/html/common/special/email-inbox/left-arrow-white.png
webgym/miniwob/html/common/special/email-inbox/left-arrow.png
webgym/miniwob/html/common/special/email-inbox/reply.png
webgym/miniwob/html/common/special/email-inbox/search.png
webgym/miniwob/html/common/special/email-inbox/send.png
webgym/miniwob/html/common/special/email-inbox/star-clicked.png
webgym-1.0.6.dist-info/METADATA
webgym-1.0.6.dist-info/WHEEL
webgym-1.0.6.dist-info/top_level.txt
webgym-1.0.6.dist-info/RECORD
