Metadata-Version: 2.1
Name: webgym
Version: 1.0.6
Summary: Reinforcement Learning Environments for 50+ web-based tasks
Home-page: https://github.com/praveen-palanisamy/webgym
Author: Praveen Palanisamy
Author-email: praveen.palanisamy@outlook.com
License: UNKNOWN
Project-URL: Source, https://github.com/praveen-palanisamy/Tensorflow-2-Reinforcement-Learning-Cookbook
Project-URL: Author website, https://praveenp.com
Keywords: webgym,rl web tasks,rl in browser,Gym environments
Platform: UNKNOWN
Classifier: Development Status :: 5 - Production/Stable
Classifier: Intended Audience :: Science/Research
Classifier: Intended Audience :: Developers
Classifier: Intended Audience :: Education
Classifier: Topic :: Scientific/Engineering
Classifier: Topic :: Scientific/Engineering :: Artificial Intelligence
Classifier: License :: OSI Approved :: MIT License
Classifier: Programming Language :: Python :: 3
Classifier: Programming Language :: Python :: 3.6
Classifier: Programming Language :: Python :: 3.7
Classifier: Programming Language :: Python :: 3.8
Classifier: Programming Language :: Python :: 3.9
Classifier: Programming Language :: Python :: 3 :: Only
Requires-Python: >=3.6, <4
Requires-Dist: gym
